LICENSE
MANIFEST.in
README.md
setup.py
src/CHA.py
src/CustomDebugFormatter.py
src/__init__.py
src/main.py
src/utils.py
src/OpenCH.egg-info/PKG-INFO
src/OpenCH.egg-info/SOURCES.txt
src/OpenCH.egg-info/dependency_links.txt
src/OpenCH.egg-info/requires.txt
src/OpenCH.egg-info/top_level.txt
src/datapipes/__init__.py
src/datapipes/datapipe.py
src/datapipes/datapipe_types.py
src/datapipes/initialize_datapipe.py
src/datapipes/memory.py
src/datapipes/types.py
src/interface/__init__.py
src/interface/base.py
src/llms/__init__.py
src/llms/anthropic.py
src/llms/initialize_llm.py
src/llms/llm.py
src/llms/llm_types.py
src/llms/openai.py
src/llms/types.py
src/orchestrator/__init__.py
src/orchestrator/action.py
src/orchestrator/orchestrator.py
src/planners/__init__.py
src/planners/action.py
src/planners/initialize_planner.py
src/planners/planner.py
src/planners/planner_types.py
src/planners/tree_of_thought.py
src/planners/types.py
src/planners/react/__init__.py
src/planners/react/base.py
src/response_generators/__init__.py
src/response_generators/initialize_response_generator.py
src/response_generators/response_generator.py
src/response_generators/response_generator_types.py
src/response_generators/types.py
src/tasks/__init__.py
src/tasks/ask_user.py
src/tasks/google_translator.py
src/tasks/initialize_task.py
src/tasks/read_from_datapipe.py
src/tasks/run_python_code.py
src/tasks/serpapi.py
src/tasks/task.py
src/tasks/task_types.py
src/tasks/test_file.py
src/tasks/types.py
src/tasks/affect/AE.py
src/tasks/affect/Predictor.py
src/tasks/affect/__init__.py
src/tasks/affect/activity_analysis.py
src/tasks/affect/activity_get.py
src/tasks/affect/base.py
src/tasks/affect/ppg_analysis.py
src/tasks/affect/ppg_get.py
src/tasks/affect/sleep_analysis.py
src/tasks/affect/sleep_get.py
src/tasks/affect/stress_analysis.py
src/tasks/playwright/__init__.py
src/tasks/playwright/base.py
src/tasks/playwright/click.py
src/tasks/playwright/current_page.py
src/tasks/playwright/extract_hyperlinks.py
src/tasks/playwright/extract_text.py
src/tasks/playwright/get_elements.py
src/tasks/playwright/navigate.py
src/tasks/playwright/navigate_back.py
src/tasks/playwright/utils.py