Metadata-Version: 2.1
Name: OpenCH
Version: 0.2.0
Summary: Conversational Health Agents (CHAs) are interactive systems designed to enhance personalhealthcare services by engaging in empathetic conversations and processing multimodal data. 
Home-page: https://github.com/Institute4FutureHealth/CHA.git
Download-URL: https://github.com/user/reponame/archive/v_01.tar.gz
Author: Mahyar Abbasian
Author-email: example@email.com
Classifier: License :: OSI Approved :: MIT License
Classifier: Programming Language :: Python :: 3
Classifier: Operating System :: OS Independent
Requires-Python: >=3.9, <3.12
License-File: LICENSE
Requires-Dist: httpcore==1.0.2
Requires-Dist: requests
Requires-Dist: gradio
Requires-Dist: pydantic
Requires-Dist: scipy
Provides-Extra: all
Requires-Dist: anthropic; extra == "all"
Requires-Dist: aiohttp; extra == "all"
Requires-Dist: google-search-results; extra == "all"
Requires-Dist: pdfminer.six; extra == "all"
Requires-Dist: googletrans-py; extra == "all"
Requires-Dist: playwright; extra == "all"
Requires-Dist: beautifulsoup4; extra == "all"
Requires-Dist: lxml; extra == "all"
Requires-Dist: tiktoken; extra == "all"
Requires-Dist: openai~=1.2; extra == "all"
Requires-Dist: pandas; extra == "all"
Requires-Dist: scipy; extra == "all"
Requires-Dist: seaborn; extra == "all"
Requires-Dist: neurokit2; extra == "all"
Requires-Dist: torch; extra == "all"
Requires-Dist: torchvision; extra == "all"
Requires-Dist: torchdata; extra == "all"
Provides-Extra: minimum
Requires-Dist: aiohttp; extra == "minimum"
Requires-Dist: google-search-results; extra == "minimum"
Requires-Dist: pdfminer.six; extra == "minimum"
Requires-Dist: playwright; extra == "minimum"
Requires-Dist: beautifulsoup4; extra == "minimum"
Requires-Dist: lxml; extra == "minimum"
Requires-Dist: tiktoken; extra == "minimum"
Requires-Dist: openai~=1.2; extra == "minimum"
Provides-Extra: develop
Requires-Dist: sphinx; extra == "develop"
Requires-Dist: sphinx-copybutton; extra == "develop"
Requires-Dist: sphinxcontrib-video; extra == "develop"
Requires-Dist: sphinxcontrib.youtube; extra == "develop"
Requires-Dist: pydata_sphinx_theme; extra == "develop"
Requires-Dist: pytest; extra == "develop"
Requires-Dist: pytest-mock; extra == "develop"
Requires-Dist: pytest-asyncio; extra == "develop"
